{
  "version": 1,
  "stack": null,
  "topology": null,
  "appRoot": ".",
  "backendRoot": null,
  "initializedAt": null,
  "lastModified": "2026-05-02T04:32:29.965Z",
  "files": {
    "src/components/TaskForm.tsx": {
      "createdBy": "unknown",
      "lastModified": "2026-05-02T04:25:47.537Z",
      "hash": "importReact,{useState}from'react'interface"
    },
    "src/components/TaskList.tsx": {
      "createdBy": "unknown",
      "lastModified": "2026-05-02T04:25:48.433Z",
      "hash": "importReactfrom'react'interfaceTask{id:"
    }
  },
  "deleted": {},
  "plan": [
    {
      "id": "step_1777695890819",
      "status": "pending",
      "operationsCount": 1,
      "createdAt": "2026-05-02T04:24:50.819Z"
    },
    {
      "id": "step_1777695890819",
      "status": "pending",
      "operationsCount": 1,
      "createdAt": "2026-05-02T04:24:50.819Z"
    },
    {
      "id": "step_1777695890819",
      "status": "pending",
      "operationsCount": 1,
      "createdAt": "2026-05-02T04:24:50.819Z"
    },
    {
      "id": "step_1777695929558",
      "status": "pending",
      "operationsCount": 1,
      "createdAt": "2026-05-02T04:25:29.558Z"
    },
    {
      "id": "step_1777695929558",
      "status": "pending",
      "operationsCount": 1,
      "createdAt": "2026-05-02T04:25:29.558Z"
    },
    {
      "id": "step_1777695929558",
      "status": "pending",
      "operationsCount": 1,
      "createdAt": "2026-05-02T04:25:29.558Z"
    },
    {
      "id": "step_1777695929558",
      "status": "pending",
      "operationsCount": 1,
      "createdAt": "2026-05-02T04:25:29.558Z"
    },
    {
      "id": "step_1777696003305",
      "status": "pending",
      "operationsCount": 1,
      "createdAt": "2026-05-02T04:26:43.305Z"
    },
    {
      "id": "step_1777696003305",
      "status": "pending",
      "operationsCount": 1,
      "createdAt": "2026-05-02T04:26:43.305Z"
    },
    {
      "id": "step_1777696003305",
      "status": "pending",
      "operationsCount": 1,
      "createdAt": "2026-05-02T04:26:43.305Z"
    },
    {
      "id": "step_1777696349965",
      "status": "pending",
      "operationsCount": 1,
      "createdAt": "2026-05-02T04:32:29.965Z"
    },
    {
      "id": "step_1777696349965",
      "status": "pending",
      "operationsCount": 1,
      "createdAt": "2026-05-02T04:32:29.965Z"
    },
    {
      "id": "step_1777696349965",
      "status": "pending",
      "operationsCount": 1,
      "createdAt": "2026-05-02T04:32:29.965Z"
    }
  ],
  "build": {
    "lastAttempt": null,
    "success": null,
    "error": null
  },
  "supabase": null,
  "historySummary": ""
}